patoolib/__init__.py
patoolib/cli.py
patoolib/configuration.py
patoolib/fileutil.py
patoolib/log.py
patoolib/mime.py
patoolib/util.py
patoolib/programs/__init__.py
patoolib/programs/ar.py
patoolib/programs/arc.py
patoolib/programs/archmage.py
patoolib/programs/arj.py
patoolib/programs/bsdcpio.py
patoolib/programs/bsdtar.py
patoolib/programs/bzip2.py
patoolib/programs/bzip3.py
patoolib/programs/cabextract.py
patoolib/programs/chmlib.py
patoolib/programs/clzip.py
patoolib/programs/compress.py
patoolib/programs/cpio.py
patoolib/programs/dpkg.py
patoolib/programs/flac.py
patoolib/programs/genisoimage.py
patoolib/programs/gzip.py
patoolib/programs/isoinfo.py
patoolib/programs/jar.py
patoolib/programs/lbzip2.py
patoolib/programs/lcab.py
patoolib/programs/lha.py
patoolib/programs/lhasa.py
patoolib/programs/lrzip.py
patoolib/programs/lz4.py
patoolib/programs/lzip.py
patoolib/programs/lzma.py
patoolib/programs/lzop.py
patoolib/programs/mac.py
patoolib/programs/nomarch.py
patoolib/programs/p7azip.py
patoolib/programs/p7rzip.py
patoolib/programs/p7zip.py
patoolib/programs/p7zz.py
patoolib/programs/p7zzs.py
patoolib/programs/pbzip2.py
patoolib/programs/pdlzip.py
patoolib/programs/pigz.py
patoolib/programs/plzip.py
patoolib/programs/py_bz2.py
patoolib/programs/py_echo.py
patoolib/programs/py_gzip.py
patoolib/programs/py_lzma.py
patoolib/programs/py_tarfile.py
patoolib/programs/py_zipfile.py
patoolib/programs/py_zstd.py
patoolib/programs/rar.py
patoolib/programs/rpm.py
patoolib/programs/rpm2cpio.py
patoolib/programs/rzip.py
patoolib/programs/shar.py
patoolib/programs/shorten.py
patoolib/programs/star.py
patoolib/programs/tar.py
patoolib/programs/unace.py
patoolib/programs/unadf.py
patoolib/programs/unalz.py
patoolib/programs/unar.py
patoolib/programs/uncompress.py
patoolib/programs/unrar.py
patoolib/programs/unshar.py
patoolib/programs/unzip.py
patoolib/programs/xdms.py
patoolib/programs/xz.py
patoolib/programs/zip.py
patoolib/programs/zoo.py
patoolib/programs/zopfli.py
patool-4.0.2.dist-info/METADATA
patool-4.0.2.dist-info/WHEEL
patool-4.0.2.dist-info/entry_points.txt
patool-4.0.2.dist-info/top_level.txt
patool-4.0.2.dist-info/RECORD
