Metadata-Version: 2.4
Name: patool
Version: 4.0.2
Summary: portable archive file manager
Home-page: https://github.com/wummel/patool
Author: Bastian Kleineidam
Author-email: bastian.kleineidam@web.de
License: GPL-3
Project-URL: Source, https://github.com/wummel/patool
Keywords: archiver,archive,compression,commandline,manager
Classifier: Environment :: Console
Classifier: Topic :: System :: Archiving :: Compression
Classifier: Development Status :: 5 - Production/Stable
Classifier: License :: OSI Approved :: GNU General Public License v3 (GPLv3)
Classifier: Programming Language :: Python :: 3
Classifier: Programming Language :: Python :: 3.11
Classifier: Programming Language :: Python :: 3.12
Classifier: Programming Language :: Python :: 3.13
Classifier: Operating System :: OS Independent
Requires-Python: >=3.11
Provides-Extra: argcompletion
Requires-Dist: argcomplete==3.6.2; extra == "argcompletion"
Dynamic: author
Dynamic: author-email
Dynamic: classifier
Dynamic: description
Dynamic: description-content-type
Dynamic: home-page
Dynamic: keywords
Dynamic: license
Dynamic: project-url
Dynamic: requires-python
Dynamic: summary
